DGR_package/BlastXML_to_alignment_module.py
DGR_package/DGR_module.py
DGR_package/__init__.py
DGR_package/generate_VR_TR_RT_summary_table_module.py
DGR_package/parse_hmmer_module.py
DGR_package/run_module.py
DGR_package/sliding_window_master_module.py
DGR_package/data/Custom_DGR_RT.hmm
DGR_package-0.0.2.dist-info/LICENSE
DGR_package-0.0.2.dist-info/METADATA
DGR_package-0.0.2.dist-info/WHEEL
DGR_package-0.0.2.dist-info/top_level.txt
DGR_package-0.0.2.dist-info/RECORD
