Metadata-Version: 2.1
Name: DGR-package
Version: 0.0.2
Summary: A DGR-finding package
Home-page: https://github.com/The-Paul-Lab/DGR_package.git
Author: Anakha Ganesh
Author-email: anakhag07@gmail.com
Project-URL: Bug Tracker, https://github.com/The-Paul-Lab/DGR_package.git
Classifier: Programming Language :: Python :: 3
Classifier: License :: OSI Approved :: MIT License
Classifier: Operating System :: OS Independent
Requires-Python: >=3.6
License-File: LICENSE
